[
  {
    "id": "lesson-01",
    "title": "SQL SELECT Basics",
    "slug": "sql-select-basics",
    "course": "intro-sql",
    "order": 1,
    "dataset_urls": ["https://raw.githubusercontent.com/ajaykumar2010/sample-datasets/main/customers.csv"],
    "starter_sql": "SELECT * FROM customers;",
    "grading": {
      "type": "result_match",
      "expected": { "columns": ["customer_id","name","city"], "row_count": 10, "order_matters": false }
    },
    "hints": ["Check the column names exactly."]
  },
  {
    "id": "lesson-02",
    "title": "Selecting Specific Columns",
    "slug": "select-columns",
    "course": "intro-sql",
    "order": 2,
    "dataset_urls": ["https://raw.githubusercontent.com/ajaykumar2010/sample-datasets/main/customers.csv"],
    "starter_sql": "SELECT name, city FROM customers;",
    "grading": { "type": "assertion_sql", "checks": ["SELECT COUNT(*)=10"] },
    "hints": ["Make sure you selected only name and city."]
  }
  // replicate entries 3–10 similarly, reusing the same dataset to start
]
